{
    "version": "s220812.964d60f",
    "source": {
        "channel": "nixpkgs-unstable",
        "revision": "964d60ff2e6bc76c0618962da52859603784fa78"
    },
    "platform": {
        "i686-linux": {
            "store": "indices/index-i686-linux",
            "hash": "sha256-OvfZNrRkbCf8yewhlqD6zSpJlIZBMQMDyOeahsT16tc="
        },
        "aarch64-linux": {
            "store": "indices/index-aarch64-linux",
            "hash": "sha256-YMQTIFhSqZdFyOS2QUehuD9uE3glZe912U3diB7PNj4="
        },
        "aarch64-darwin": {
            "store": "indices/index-aarch64-darwin",
            "hash": "sha256-7noTcztnLzswkLSIVhTVz9P5l4Y/3aj/E71pygvU60g="
        },
        "x86_64-darwin": {
            "store": "indices/index-x86_64-darwin",
            "hash": "sha256-TMp8Wo8vrJ6vT8dlZ6LAMRiCMMVnP7MB6hZWDnLhSXQ="
        },
        "x86_64-linux": {
            "store": "indices/index-x86_64-linux",
            "hash": "sha256-uMyn7DX9uW5f3hZAxPf+n1dtEO1csTXH4zIHJ6Nw7Hs="
        }
    }
}
